odoo/addons/web_widget_x2many_2d_matrix/README.rst
odoo/addons/web_widget_x2many_2d_matrix/__init__.py
odoo/addons/web_widget_x2many_2d_matrix/__manifest__.py
odoo/addons/web_widget_x2many_2d_matrix/demo/res_groups_views.xml
odoo/addons/web_widget_x2many_2d_matrix/i18n/ar.po
odoo/addons/web_widget_x2many_2d_matrix/i18n/de.po
odoo/addons/web_widget_x2many_2d_matrix/i18n/es.po
odoo/addons/web_widget_x2many_2d_matrix/i18n/fi.po
odoo/addons/web_widget_x2many_2d_matrix/i18n/fr.po
odoo/addons/web_widget_x2many_2d_matrix/i18n/hr.po
odoo/addons/web_widget_x2many_2d_matrix/i18n/it.po
odoo/addons/web_widget_x2many_2d_matrix/i18n/lt.po
odoo/addons/web_widget_x2many_2d_matrix/i18n/nl.po
odoo/addons/web_widget_x2many_2d_matrix/i18n/nl_NL.po
odoo/addons/web_widget_x2many_2d_matrix/i18n/pt_BR.po
odoo/addons/web_widget_x2many_2d_matrix/i18n/sl.po
odoo/addons/web_widget_x2many_2d_matrix/i18n/tr.po
odoo/addons/web_widget_x2many_2d_matrix/i18n/web_widget_x2many_2d_matrix.pot
odoo/addons/web_widget_x2many_2d_matrix/i18n/zh_CN.po
odoo/addons/web_widget_x2many_2d_matrix/readme/CONTRIBUTORS.md
odoo/addons/web_widget_x2many_2d_matrix/readme/DESCRIPTION.md
odoo/addons/web_widget_x2many_2d_matrix/readme/HISTORY.md
odoo/addons/web_widget_x2many_2d_matrix/readme/ROADMAP.md
odoo/addons/web_widget_x2many_2d_matrix/readme/USAGE.md
odoo/addons/web_widget_x2many_2d_matrix/static/description/icon.png
odoo/addons/web_widget_x2many_2d_matrix/static/description/index.html
odoo/addons/web_widget_x2many_2d_matrix/static/description/screenshot.png
odoo/addons/web_widget_x2many_2d_matrix/static/src/components/x2many_2d_matrix_field/x2many_2d_matrix_field.esm.js
odoo/addons/web_widget_x2many_2d_matrix/static/src/components/x2many_2d_matrix_field/x2many_2d_matrix_field.scss
odoo/addons/web_widget_x2many_2d_matrix/static/src/components/x2many_2d_matrix_field/x2many_2d_matrix_field.xml
odoo/addons/web_widget_x2many_2d_matrix/static/src/components/x2many_2d_matrix_renderer/x2many_2d_matrix_renderer.esm.js
odoo_addon_web_widget_x2many_2d_matrix-18.0.2.0.3.1.dist-info/METADATA
odoo_addon_web_widget_x2many_2d_matrix-18.0.2.0.3.1.dist-info/WHEEL
odoo_addon_web_widget_x2many_2d_matrix-18.0.2.0.3.1.dist-info/top_level.txt
odoo_addon_web_widget_x2many_2d_matrix-18.0.2.0.3.1.dist-info/RECORD
