Metadata-Version: 2.1
Name: odoo-addon-web_widget_x2many_2d_matrix
Version: 18.0.2.0.3.1
Requires-Python: >=3.10
Requires-Dist: odoo==18.0.*
Summary: Show list fields as a matrix
Home-page: https://github.com/OCA/web
License: AGPL-3
Author: Hunki Enterprises BV, Therp BV, Tecnativa, Camptocamp, CorporateHub, Onestein, Odoo Community Association (OCA)
Author-email: support@odoo-community.org
Classifier: Programming Language :: Python
Classifier: Framework :: Odoo
Classifier: Framework :: Odoo :: 18.0
Classifier: License :: OSI Approved :: GNU Affero General Public License v3
Classifier: Development Status :: 5 - Production/Stable
